XStatic_bootswatch-3.3.7.0-py2.7-nspkg.pth
XStatic_bootswatch-3.3.7.0.dist-info/DESCRIPTION.rst
XStatic_bootswatch-3.3.7.0.dist-info/METADATA
XStatic_bootswatch-3.3.7.0.dist-info/RECORD
XStatic_bootswatch-3.3.7.0.dist-info/WHEEL
XStatic_bootswatch-3.3.7.0.dist-info/metadata.json
XStatic_bootswatch-3.3.7.0.dist-info/namespace_packages.txt
XStatic_bootswatch-3.3.7.0.dist-info/top_level.txt
xstatic/pkg/bootswatch/__init__.py
xstatic/pkg/bootswatch/data/README.md
xstatic/pkg/bootswatch/data/cerulean/_bootswatch.scss
xstatic/pkg/bootswatch/data/cerulean/_variables.scss
xstatic/pkg/bootswatch/data/cerulean/bootstrap.css
xstatic/pkg/bootswatch/data/cerulean/bootstrap.min.css
xstatic/pkg/bootswatch/data/cerulean/bootswatch.less
xstatic/pkg/bootswatch/data/cerulean/index.html
xstatic/pkg/bootswatch/data/cerulean/thumbnail.png
xstatic/pkg/bootswatch/data/cerulean/variables.less
xstatic/pkg/bootswatch/data/cosmo/_bootswatch.scss
xstatic/pkg/bootswatch/data/cosmo/_variables.scss
xstatic/pkg/bootswatch/data/cosmo/bootstrap.css
xstatic/pkg/bootswatch/data/cosmo/bootstrap.min.css
xstatic/pkg/bootswatch/data/cosmo/bootswatch.less
xstatic/pkg/bootswatch/data/cosmo/index.html
xstatic/pkg/bootswatch/data/cosmo/thumbnail.png
xstatic/pkg/bootswatch/data/cosmo/variables.less
xstatic/pkg/bootswatch/data/cyborg/_bootswatch.scss
xstatic/pkg/bootswatch/data/cyborg/_variables.scss
xstatic/pkg/bootswatch/data/cyborg/bootstrap.css
xstatic/pkg/bootswatch/data/cyborg/bootstrap.min.css
xstatic/pkg/bootswatch/data/cyborg/bootswatch.less
xstatic/pkg/bootswatch/data/cyborg/index.html
xstatic/pkg/bootswatch/data/cyborg/thumbnail.png
xstatic/pkg/bootswatch/data/cyborg/variables.less
xstatic/pkg/bootswatch/data/darkly/_bootswatch.scss
xstatic/pkg/bootswatch/data/darkly/_variables.scss
xstatic/pkg/bootswatch/data/darkly/bootstrap.css
xstatic/pkg/bootswatch/data/darkly/bootstrap.min.css
xstatic/pkg/bootswatch/data/darkly/bootswatch.less
xstatic/pkg/bootswatch/data/darkly/index.html
xstatic/pkg/bootswatch/data/darkly/thumbnail.png
xstatic/pkg/bootswatch/data/darkly/variables.less
xstatic/pkg/bootswatch/data/flatly/_bootswatch.scss
xstatic/pkg/bootswatch/data/flatly/_variables.scss
xstatic/pkg/bootswatch/data/flatly/bootstrap.css
xstatic/pkg/bootswatch/data/flatly/bootstrap.min.css
