Metadata-Version: 2.0
Name: XStatic-bootswatch
Version: 3.3.7.0
Summary: bootswatch 3.3.7 (XStatic packaging standard)
Home-page: http://bootswatch.com
Author: Rob Cresswell
Author-email: robert.cresswell@outlook.com
License: MIT
Keywords: bootswatch xstatic
Platform: any
